{
  "code": 200,
  "data": [
    {
      "id": "1976870103505702914",
      "title": "(Sulih suara) Salah Pilih Cinta",
      "cover": "https://awscover.netshort.com/tos-vod-mya-v-da59d5a2040f5f77/coverG/prod/1636562710_20251108-113842.jpg~tplv-vod-rs:540:720.webp"
    },
    {
      "id": "1953726106705170434",
      "title": "(Sulih suara)Rahasia Miliarder di Balik Wajah Biasa",
      "cover": "https://awscover.netshort.com/tos-vod-mya-v-da59d5a2040f5f77/imageG/prod/1953726066435784706/1755512543459-9390894634800574-3比4jpg~tplv-vod-rs:540:720.webp"
    },
    {
      "id": "1896782117933649921",
      "title": "Kenapa Menangis Setelah Tahu Siapa Aku",
      "cover": "https://awscover.netshort.com/tos-vod-mya-v-da59d5a2040f5f77/coverG/test/1611722279_知道我身份后你哭什么印尼.jpg~tplv-vod-rs:540:720.webp"
    },
    {
      "id": "1997949622037180417",
      "title": "(Sulih suara) Jagal Tak Terkalahkan",
      "cover": "https://awscover.netshort.com/tos-vod-mya-v-da59d5a2040f5f77/coverG/prod/-1594179841_我凭一把屠刀问鼎江湖印尼语.jpg~tplv-vod-rs:540:720.webp"
    },
    {
      "id": "2013184618975076354",
      "title": "Legenda yang Tersembunyi",
      "cover": "https://awscover.netshort.com/tos-vod-mya-v-da59d5a2040f5f77/imageG/production/2013184028168617986/1769487121045-9360907070245741-3比4jpg~tplv-vod-rs:540:720.webp"
    }
  ]
}